[{
    "skill": "Java",
    "skill_level": 3,
    "interest_level": 4, 
    "category": "language"
},
{
    "skill": "C++",
    "skill_level": 3,
    "interest_level": 4, 
    "category": "language"
},
{
    "skill": "C",
    "skill_level": 2,
    "interest_level": 4, 
    "category": "language"
},
{
    "skill": "HTML",
    "skill_level": 4,
    "interest_level": 4, 
    "category": "language"
},
{
    "skill": "Design",
    "skill_level": 4,
    "interest_level": 1, 
    "category": "other"
},
{
    "skill": "CSS",
    "skill_level": 4,
    "interest_level": 4, 
    "category": "language"
},
{
    "skill": "Angular",
    "skill_level": 3,
    "interest_level": 5, 
    "category": "framework"
},
{
    "skill": "Photoshop",
    "skill_level": 3,
    "interest_level": 2, 
    "category": "software"
},
{
    "skill": "Illustrator",
    "skill_level": 3,
    "interest_level": 3, 
    "category": "software"
},
{
    "skill": "Laravel",
    "skill_level": 3,
    "interest_level": 5, 
    "category": "framework"
},
{
    "skill": "React",
    "skill_level": 1,
    "interest_level": 5, 
    "category": "framework"
},
{
    "skill": "SQL",
    "skill_level": 2,
    "interest_level": 4, 
    "category": "language"
},
{
    "skill": "Ionic",
    "skill_level": 3,
    "interest_level": 4, 
    "category": "framework"
}
]